rdconfig/__init__.py
rdconfig/config.py
rdconfig/glb.py
rdconfig/global.py
rdconfig/private.py
rdconfig/protect.py
rdcrm/__init__.py
rdcrm/customer.py
rdcrm/login.py
rdcrm/product.py
rdcrm/salesOrder.py
rdcrm/bill/__init__.py
rdcrm/bill/salesOrder.py
rdcrm/md/__init__.py
rdcrm/md/customer.py
rdcrm/md/product.py
rdconfig-1.3.4.dist-info/LICENSE
rdconfig-1.3.4.dist-info/METADATA
rdconfig-1.3.4.dist-info/WHEEL
rdconfig-1.3.4.dist-info/top_level.txt
rdconfig-1.3.4.dist-info/RECORD
