Metadata-Version: 2.1
Name: rdconfig
Version: 1.3.4
Summary: read config file in py language 
Home-page: http://www.reshapedata.com
Author: hulilei
Author-email: hulilei@takewiki.com.cn
License: Apache License
Keywords: reshapedata,cdconfig
Platform: UNKNOWN
Requires-Python: >=3.6
License-File: LICENSE
Requires-Dist: requests
